kicad_draw/PCBmodule.py
kicad_draw/__init__.py
kicad_draw/cli.py
kicad_draw/config.py
kicad_draw/constants.py
kicad_draw/formatter.py
kicad_draw/geometry.py
kicad_draw/layers.py
kicad_draw/models.py
kicad_draw/visualizer.py
kicad_draw-0.5.2.dist-info/METADATA
kicad_draw-0.5.2.dist-info/WHEEL
kicad_draw-0.5.2.dist-info/entry_points.txt
kicad_draw-0.5.2.dist-info/licenses/LICENSE
kicad_draw-0.5.2.dist-info/RECORD
