Metadata-Version: 2.4
Name: kicad-draw
Version: 0.5.2
Summary: Python module for generating traces for KiCad PCB.
Author-email: t-sasatani <sasatani.dev@gmail.com>
License-File: LICENSE
Requires-Python: <4.0,>=3.11
Requires-Dist: black[jupyter]<26,>=25.1.0
Requires-Dist: click<9,>=8.1.7
Requires-Dist: ipykernel<7,>=6.29.5
Requires-Dist: isort<7,>=6.0.1
Requires-Dist: myst-parser<5,>=4.0.1
Requires-Dist: numpy<3,>=2.3.0
Requires-Dist: pydantic<3,>=2.0.0
Requires-Dist: pytest-cov<7,>=6.0.0
Requires-Dist: pytest<9,>=8.0.0
Requires-Dist: ruff<0.12,>=0.11.6
Requires-Dist: sphinx-rtd-theme<4,>=3.0.2
Requires-Dist: sphinx<9,>=8.1.3
Provides-Extra: dev
Requires-Dist: build<2,>=1.0.0; extra == 'dev'
Requires-Dist: pytest-cov<7,>=6.0.0; extra == 'dev'
Requires-Dist: pytest-mock<4,>=3.12.0; extra == 'dev'
Requires-Dist: pytest<9,>=8.0.0; extra == 'dev'
Provides-Extra: docs
Requires-Dist: myst-parser<5,>=4.0.1; extra == 'docs'
Requires-Dist: sphinx-rtd-theme<4,>=3.0.2; extra == 'docs'
Requires-Dist: sphinx<9,>=8.1.3; extra == 'docs'
Provides-Extra: viz
Requires-Dist: matplotlib<4,>=3.5.0; extra == 'viz'
